[
    {"title": "Пачка сигарет (A Pack of Cigarettes)", "artist": "Kino", "src": "https://file.garden/aKopybLZKBsHizm5/packofcigs" },
    {"title": "Печаль (Sorrow)", "artist": "Kino", "src": "https://file.garden/aKopybLZKBsHizm5/sorrow" },
    {"title": "Звезда по имени Солнце (A Star Called the Sun)", "artist": "Kino", "src": "https://file.garden/aKopybLZKBsHizm5/starcalledsun" },
    {"title": "Лето (Summer)", "artist": "Kino", "src": "https://file.garden/aKopybLZKBsHizm5/summer" },
    {"title": "Нам с тобой (To Me and You)", "artist": "Kino", "src": "https://file.garden/aKopybLZKBsHizm5/youandi" },
    {"title": "В наших глазах (In Our Eyes)", "artist": "Kino", "src": "https://file.garden/aKopybLZKBsHizm5/inoureyes" },
    {"title": "Бездельник №1 (Slacker No.1)", "artist": "Kino", "src": "https://file.garden/aKopybLZKBsHizm5/neet" }
]
